azure/messaging/webpubsubclient/__init__.py
azure/messaging/webpubsubclient/_client.py
azure/messaging/webpubsubclient/_model_base.py
azure/messaging/webpubsubclient/_util.py
azure/messaging/webpubsubclient/_version.py
azure/messaging/webpubsubclient/py.typed
azure/messaging/webpubsubclient/aio/__init__.py
azure/messaging/webpubsubclient/aio/_client.py
azure/messaging/webpubsubclient/models/__init__.py
azure/messaging/webpubsubclient/models/_enums.py
azure/messaging/webpubsubclient/models/_models.py
azure_messaging_webpubsubclient-1.1.0.dist-info/LICENSE
azure_messaging_webpubsubclient-1.1.0.dist-info/METADATA
azure_messaging_webpubsubclient-1.1.0.dist-info/WHEEL
azure_messaging_webpubsubclient-1.1.0.dist-info/top_level.txt
azure_messaging_webpubsubclient-1.1.0.dist-info/RECORD
