Metadata-Version: 2.1
Name: azure-messaging-webpubsubclient
Version: 1.1.0
Summary: Microsoft Azure Web PubSub Client Library for Python
Home-page: https://github.com/Azure/azure-sdk-for-python/tree/main/sdk
Author: Microsoft Corporation
Author-email: azpysdkhelp@microsoft.com
License: MIT License
Keywords: azure,azure sdk
Classifier: Development Status :: 5 - Production/Stable
Classifier: Programming Language :: Python
Classifier: Programming Language :: Python :: 3 :: Only
Classifier: Programming Language :: Python :: 3
Classifier: Programming Language :: Python :: 3.8
Classifier: Programming Language :: Python :: 3.9
Classifier: Programming Language :: Python :: 3.10
Classifier: Programming Language :: Python :: 3.11
Classifier: Programming Language :: Python :: 3.12
Classifier: License :: OSI Approved :: MIT License
Requires-Python: >=3.8
License-File: LICENSE
Requires-Dist: isodate (>=0.6.1)
Requires-Dist: azure-core (>=1.26.3)
Requires-Dist: websocket-client (>=1.6.0)
Provides-Extra: aio
Requires-Dist: aiohttp (>=3.9.3) ; extra == 'aio'
